README.rst
setup.py
succession/__init__.py
succession.egg-info/PKG-INFO
succession.egg-info/SOURCES.txt
succession.egg-info/dependency_links.txt
succession.egg-info/not-zip-safe
succession.egg-info/top_level.txt
succession/tests/__init__.py