Metadata-Version: 1.1
Name: succession
Version: 0.3.0
Summary: A python library providing concurrent push based lazy linked lists
Home-page: https://github.com/bwhmather/succession
Author: Ben Mather
Author-email: bwhmather@bwhmather.com
License: BSD
Platform: UNKNOWN
Classifier: Development Status :: 4 - Beta
Classifier: Intended Audience :: Developers
Classifier: License :: OSI Approved :: BSD License
Classifier: Operating System :: OS Independent
Classifier: Programming Language :: Python :: 3
